{"animations":[{"anim":"singRIGHT","fps":24,"indices":[],"loop":false,"name":"Right","offsets":[0,0]},{"anim":"singDOWN","fps":24,"indices":[],"loop":false,"name":"Down","offsets":[0,0]},{"anim":"singLEFT","fps":24,"indices":[],"loop":false,"name":"Left","offsets":[0,0]},{"anim":"singUP","fps":24,"indices":[],"loop":false,"name":"Up","offsets":[0,0]},{"anim":"idle","fps":24,"loop":false,"name":"Idle","offsets":[0,0]}],"camera_position":[500,-150],"flip_x":false,"healthbar_colors":[117,103,137],"healthicon":"grayBebe","image":"characters/greyBaby","no_antialiasing":false,"position":[-20,300],"scale":0.7,"sing_duration":10}